project1/EE671_Project1_Team48/Verilog/a21oi.v
module logic_gate (
    input a1,
    input a2,
    input b1,
    output y
);
    assign y = ~((a1 & a2) | b1);
endmodule

project1/a21oi/tb_a21oi.v
`timescale 1ns/1ps

module tb;
    reg a1, a2, b1;
    wire y;

    logic_gate dut(.a1(a1), .a2(a2), .b1(b1), .y(y));

    initial begin
        $dumpfile("dump.vcd");
        $dumpvars(0, tb);

        a1=0; a2=0; b1=0; #10;
        a1=0; a2=0; b1=1; #10;
        a1=0; a2=1; b1=0; #10;
        a1=0; a2=1; b1=1; #10;
        a1=1; a2=0; b1=0; #10;
        a1=1; a2=0; b1=1; #10;
        a1=1; a2=1; b1=0; #10;
        a1=1; a2=1; b1=1; #10;

        $finish;
    end
endmodule

project1/a21oi/dump.vcd
$date
	Sat Sep 13 21:06:58 2025
$end
$version
	Icarus Verilog
$end
$timescale
	1ps
$end
$scope module tb $end
$var wire 1 ! y $end
$var reg 1 " a1 $end
$var reg 1 # a2 $end
$var reg 1 $ b1 $end
$scope module dut $end
$var wire 1 " a1 $end
$var wire 1 # a2 $end
$var wire 1 $ b1 $end
$var wire 1 ! y $end
$upscope $end
$upscope $end
$enddefinitions $end
$comment Show the parameter values. $end
$dumpall
$end
#0
$dumpvars
0$
0#
0"
1!
$end
#10000
0!
1$
#20000
1!
0$
1#
#30000
0!
1$
#40000
1!
0$
0#
1"
#50000
0!
1$
#60000
0$
1#
#70000
1$
